candle_driver.cp312-win_amd64.pyd
candle_bus/__init__.py
candle_bus/candle_bus.py
candle_bus-1.2.dist-info/METADATA
candle_bus-1.2.dist-info/WHEEL
candle_bus-1.2.dist-info/entry_points.txt
candle_bus-1.2.dist-info/top_level.txt
candle_bus-1.2.dist-info/RECORD
