Metadata-Version: 2.1
Name: candle_bus
Version: 1.2
Summary: Python Can plugin with windows candle driver.
Author: song
Author-email: zhaosongy@126.com
Maintainer: robottime
Maintainer-email: lab@robottime.cn
License: MIT License
Keywords: candle,python_can,can
Classifier: License :: OSI Approved :: MIT License
Classifier: Operating System :: Microsoft :: Windows
Classifier: Intended Audience :: Developers
Classifier: Programming Language :: Python :: 3 :: Only
Classifier: Programming Language :: Python :: 3.6
Classifier: Programming Language :: Python :: 3.7
Classifier: Programming Language :: Python :: 3.8
Classifier: Programming Language :: Python :: 3.9
Classifier: Programming Language :: Python :: 3.10
Classifier: Programming Language :: Python :: 3.11
Classifier: Programming Language :: Python :: 3.12
Classifier: Programming Language :: Python :: 3.13
Classifier: Programming Language :: Python :: 3.14
Requires-Python: >=3.6
Requires-Dist: python-can <4.0,>=3.2.0
